rqcopt/__init__.py
rqcopt/brickwall_circuit.py
rqcopt/brickwall_opt.py
rqcopt/splitting_method.py
rqcopt/trust_region.py
rqcopt/util.py
rqcopt-1.0.0.dist-info/LICENSE
rqcopt-1.0.0.dist-info/METADATA
rqcopt-1.0.0.dist-info/WHEEL
rqcopt-1.0.0.dist-info/top_level.txt
rqcopt-1.0.0.dist-info/RECORD
