Metadata-Version: 2.1
Name: rqcopt
Version: 1.0.0
Summary: Python package for Riemannian quantum circuit optimization
Home-page: https://github.com/qc-tum/rqcopt
Author: Christian B. Mendl
Author-email: "Christian B. Mendl" <christian.b.mendl@gmail.com>
License: Apache-2.0
Project-URL: Homepage, https://github.com/qc-tum/rqcopt
Requires-Python: >=3.7
License-File: LICENSE
Requires-Dist: numpy
Requires-Dist: scipy
